faff_core-0.1.16.dist-info/METADATA
faff_core-0.1.16.dist-info/WHEEL
faff_core/__init__.py
faff_core/faff_core.cpython-313-x86_64-linux-gnu.so
faff_core/faff_core.pyi
faff_core/plugins.py
faff_core-0.1.16.dist-info/RECORD
