Metadata-Version: 2.4
Name: faff-core
Version: 0.1.16
Classifier: Programming Language :: Rust
Classifier: Programming Language :: Python :: Implementation :: CPython
Classifier: Programming Language :: Python :: 3.11
Classifier: Programming Language :: Python :: 3.12
Classifier: Programming Language :: Python :: 3.13
Classifier: License :: OSI Approved :: GNU Affero General Public License v3 or later (AGPLv3+)
Summary: Core library for the Faffage time tracking ecosystem.
License: AGPL-3.0-or-later
Requires-Python: >=3.11
Project-URL: Homepage, https://github.com/faffhub/faff-core
Project-URL: Repository, https://github.com/faffhub/faff-core
Project-URL: Issues, https://github.com/faffhub/faff-core/issues
